API.cp39-win_amd64.pyd
main.cp39-win_amd64.pyd
View/__init__.cp39-win_amd64.pyd
View/file.cp39-win_amd64.pyd
View/scheduler.cp39-win_amd64.pyd
src/__init__.py
src/setup.py
src/cp_api/API.py
src/cp_api/__init__.py
src/cp_api/main.py
src/cp_api/View/__init__.py
src/cp_api/View/file.py
src/cp_api/View/scheduler.py
xiwang_cp_API-1.0.0.0.dist-info/LICENSE
xiwang_cp_API-1.0.0.0.dist-info/METADATA
xiwang_cp_API-1.0.0.0.dist-info/WHEEL
xiwang_cp_API-1.0.0.0.dist-info/top_level.txt
xiwang_cp_API-1.0.0.0.dist-info/RECORD
