Metadata-Version: 2.1
Name: xiwang_cp_API
Version: 1.0.0.0
Summary: flask的API插件
Home-page: https://www.xi-wang.cn
Download-URL: https://www.xi-wang.cn/download/
Author: xiwang
Author-email: xiwang0439@hotmail.com
Keywords: pack,api
Classifier: Programming Language :: Python :: 3
Classifier: License :: OSI Approved :: MIT License
Classifier: Operating System :: OS Independent
Requires-Python: >=3
License-File: LICENSE
Requires-Dist: flask
